{
  "Time": "14",
  "Title": "Strategy Tester Report",
  "EA Name": "EA31337-Rider-b4f5b55719ea75ca8e363cbe0036bcf3dc50cb6e",
  "Build": "1280",
  "Symbol": "EURUSD (Euro vs US Dollar)",
  "Period": "1 Minute (M1)  2020.01.01 23:41 - 2020.12.30 23:59    (2020.01.01 - 2020.12.31)",
  "Model": "Every tick ",
  "Initial deposit": "1000.00",
  "Spread": "1",
  "Modelling quality": "24.99%",
  "Parameters": "__EA_Mode_Parameters__=&#34;-- EA parameters for EA31337 Rider v2.003 --&#34;; __Strategies_Active__=&#34;-- Active strategies --&#34;; Strategy_M1=0; Strategy_M5=0; Strategy_M15=14; Strategy_M30=14; __EA_Stops__=&#34;-- EA&#39;s stops --&#34;; EA_Stops=22; __Trade_Params__=&#34;-- EA&#39;s trade parameters --&#34;; EA_LotSize=0.01; EA_SignalOpenFilter=37; __EA_Risk_Params__=&#34;-- EA&#39;s risk management --&#34;; EA_Risk_MarginMax=10; __EA_Logging_Parameters__=&#34;-- Settings for logging &amp; messages --&#34;; VerboseLevel=3; __EA_Other_Parameters__=&#34;-- Other parameters --&#34;; EA_DisplayDetailsOnChart=true; ,EA_MagicNumber=31337; __EA_Parameters__=&#34;-- End of input parameters for EA31337 Rider v2.003 --&#34;; ",
  "Bars in test": "372155",
  "Ticks modelled": "167831773",
  "Mismatched charts errors": "0",
  "Total net profit": "2.70",
  "Gross profit": "11.10",
  "Gross loss": "-8.40",
  "Profit factor": "1.32",
  "Expected payoff": "0.13",
  "Absolute drawdown": "2.10",
  "Maximal drawdown": "3.10 (0.31%)",
  "Relative drawdown": "0.31% (3.10)",
  "Total trades": "21",
  "Short positions": "17 (58.82%)",
  "Long positions": "4 (75.00%)",
  "Profit trades": "13 (61.90%)",
  "Loss trades": "8 (38.10%)",
  "profit trade": "1.00,0.85",
  "loss trade": "-1.10,-1.05",
  "consecutive wins (profit in money)": "5 (4.10)",
  "consecutive losses (loss in money)": "2 (-2.20)",
  "consecutive profit": "4.10 (5)",
  "consecutive loss": "2 (-2.20),-2.20 (2),1",
  "consecutive wins": "5 (4.10),2",
  "consecutive losses": "2 (-2.20),1"
}
